aioway/__init__.py
aioway/_errors.py
aioway/codecs.py
aioway/compilers.py
aioway/_registries/__init__.py
aioway/_registries/registries.py
aioway/_registries/types.py
aioway/attrs/__init__.py
aioway/attrs/devices.py
aioway/attrs/genres.py
aioway/attrs/shapes.py
aioway/attrs/attrs/__init__.py
aioway/attrs/attrs/attrs.py
aioway/attrs/attrs/names.py
aioway/attrs/attrs/sets.py
aioway/attrs/dtypes/__init__.py
aioway/attrs/dtypes/dtypes.py
aioway/attrs/dtypes/factories.py
aioway/attrs/dtypes/primitives.py
aioway/attrs/einsums/__init__.py
aioway/attrs/einsums/attrs.py
aioway/attrs/einsums/parsers.py
aioway/attrs/einsums/sets.py
aioway/execs/__init__.py
aioway/execs/caches.py
aioway/execs/dags.py
aioway/execs/execs.py
aioway/execs/ops.py
aioway/execs/trees.py
aioway/io/__init__.py
aioway/io/_batches.py
aioway/io/frames.py
aioway/io/pandas.py
aioway/io/streams.py
aioway/io/torch.py
aioway/io/_indices/__init__.py
aioway/io/_indices/faiss.py
aioway/io/_indices/indices.py
aioway/io/_indices/lexsort.py
aioway/io/_indices/mgrs.py
aioway/io/_indices/ops.py
aioway/losses/__init__.py
aioway/losses/dists.py
aioway/losses/losses.py
aioway/modules/__init__.py
aioway/modules/prelude.py
aioway/modules/previews.py
aioway/modules/specs/__init__.py
aioway/modules/specs/sets.py
aioway/modules/specs/specs.py
aioway/modules/specs/sympy.py
aioway/ops/__init__.py
aioway/ops/_funcs.py
aioway/ops/binary.py
aioway/ops/flat_maps.py
aioway/ops/maps.py
aioway/ops/nullary.py
aioway/ops/ops.py
aioway/ops/thunks.py
aioway/schemas/__init__.py
aioway/schemas/parsers.py
aioway/schemas/schemas.py
aioway-0.0.4.dist-info/licenses/LICENSE.md
aioway-0.0.4.dist-info/METADATA
aioway-0.0.4.dist-info/WHEEL
aioway-0.0.4.dist-info/top_level.txt
aioway-0.0.4.dist-info/RECORD
