Metadata-Version: 2.4
Name: aioway
Version: 0.0.4
Summary: AI on the way
Author-email: RenChu Wang <patrick1031wang@gmail.com>
License: Apache-2.0
Requires-Python: <4,>=3.13
License-File: LICENSE.md
Requires-Dist: lark>=1.2.2
Requires-Dist: numpy>=2.2.6
Requires-Dist: pandas>=2.2.3
Requires-Dist: rich>=14.0.0
Requires-Dist: tensordict>=0.8.3
Requires-Dist: torch>=2.7.0
Provides-Extra: ibis
Requires-Dist: ibis>=3.3.0; extra == "ibis"
Provides-Extra: faiss
Requires-Dist: faiss-cpu>=1.11.0; extra == "faiss"
Dynamic: license-file
